{
  "scan_date": "2025-11-18T09:15:56.874561",
  "symbols_scanned": 5,
  "scanned_symbols": [
    "TQQQ",
    "SP500",
    "AAPL",
    "UBER",
    "SQQQ"
  ],
  "opportunities_found": 1,
  "opportunities": [
    {
      "symbol": "TQQQ",
      "fundamentals": {
        "symbol": "TQQQ",
        "company_name": "ProShares UltraPro QQQ",
        "current_price": 102.05,
        "market_cap": 0,
        "pe_ratio": 33.410423,
        "forward_pe": null,
        "peg_ratio": null,
        "profit_margins": null,
        "revenue_growth": null,
        "52w_high": 121.37,
        "52w_low": 35.0,
        "distance_from_52w_high": 15.92,
        "5d_change": -8.7,
        "analyst_target": null,
        "recommendation": "none"
      },
      "news": [
        {
          "symbol": "TQQQ",
          "title": "",
          "publisher": "",
          "link": "",
          "published": "1969-12-31 19:00:00",
          "type": "STORY",
          "sentiment": {
            "is_opportunity": false,
            "reason": "Sentiment: neutral",
            "sentiment": "neutral",
            "sentiment_score": 0,
            "confidence": 0.5,
            "method": "finbert",
            "probabilities": {
              "positive": 0.33,
              "negative": 0.33,
              "neutral": 0.34
            }
          }
        }
      ],
      "opportunity_score": 80,
      "recommendation": "\ud83d\udfe2 STRONG BUY - Excellent opportunity"
    }
  ]
}